local_cloud_forge/__init__.py
local_cloud_forge/decorator.py
localcloudforge-0.2.0.dist-info/LICENSE
localcloudforge-0.2.0.dist-info/METADATA
localcloudforge-0.2.0.dist-info/WHEEL
localcloudforge-0.2.0.dist-info/top_level.txt
localcloudforge-0.2.0.dist-info/RECORD
