Metadata-Version: 2.1
Name: localcloudforge
Version: 0.2.0
Summary: A tool for developing and testing AWS service integrations locally.
Home-page: https://github.com/joaovitorgit/LocalCloudForge
Author: João Vitor de Faria
Author-email: joao.faria@profusion.mobi
Requires-Python: >=3.11.4
License-File: LICENSE
Requires-Dist: boto3>=1.34.123
Requires-Dist: localstack-client>=2.6
